setup.py
thunderscript/__init__.py
thunderscript/app.py
thunderscript/exceptions.py
thunderscript.egg-info/PKG-INFO
thunderscript.egg-info/SOURCES.txt
thunderscript.egg-info/dependency_links.txt
thunderscript.egg-info/requires.txt
thunderscript.egg-info/top_level.txt
thunderscript/drivers/__init__.py
thunderscript/drivers/base_parser.py
thunderscript/drivers/driver_corecluster.py
thunderscript/drivers/driver_dummy.py
thunderscript/drivers/driver_pycore.py
thunderscript/models/__init__.py
thunderscript/models/thunder/__init__.py
thunderscript/models/thunder/call.py
thunderscript/views/__init__.py
thunderscript/views/api/__init__.py
thunderscript/views/api/thunder.py