Metadata-Version: 1.1
Name: thunderscript
Version: 17.4.3
Summary: Thunder script parser
Home-page: http://cloudover.org/thunder/
Author: Maciej Nabozny
Author-email: maciej.nabozny@cloudover.io
License: UNKNOWN
Download-URL: https://github.com/cloudOver/thunder-script/archive/master.zip
Keywords: corecluster,cloudover,cloud
Platform: UNKNOWN
